sanskrit_util/__init__.py
sanskrit_util/analyze.py
sanskrit_util/context.py
sanskrit_util/generate.py
sanskrit_util/models.py
sanskrit_util/query.py
sanskrit_util/sandhi.py
sanskrit_util/schema.py
sanskrit_util/setup.py
sanskrit_util/shell.py
sanskrit_util/sounds.py
sanskrit_util/tagger.py
sanskrit_util/util/__init__.py
sanskrit_util/util/functions.py
sanskrit_util/util/queue.py
sanskrit_util/util/trie.py
sanskrit_util-0.1.2.dist-info/LICENSE
sanskrit_util-0.1.2.dist-info/METADATA
sanskrit_util-0.1.2.dist-info/WHEEL
sanskrit_util-0.1.2.dist-info/top_level.txt
sanskrit_util-0.1.2.dist-info/RECORD
