Metadata-Version: 2.1
Name: sanskrit-util
Version: 0.1.2
Summary: Sanskrit utilities
Home-page: https://github.com/avinashvarna/sanskrit_util
Author: Sanskrit Programmers
Project-URL: Bug Tracker, https://github.com/avinashvarna/sanskrit_util/issues
Classifier: Programming Language :: Python :: 3
Classifier: License :: OSI Approved :: MIT License
Classifier: Operating System :: OS Independent
Classifier: Development Status :: 3 - Alpha
License-File: LICENSE
Requires-Dist: sqlalchemy (>=1.4)
Requires-Dist: six
Provides-Extra: dev
Requires-Dist: pytest ; extra == 'dev'
Provides-Extra: test
Requires-Dist: pytest ; extra == 'test'
